LICENSE
README.md
cloudgrep.py
setup.cfg
setup.py
cloudgrep/__init__.py
cloudgrep/__main__.py
cloudgrep/cloud.py
cloudgrep/cloudgrep.py
cloudgrep/search.py
cloudgrep.egg-info/PKG-INFO
cloudgrep.egg-info/SOURCES.txt
cloudgrep.egg-info/dependency_links.txt
cloudgrep.egg-info/entry_points.txt
cloudgrep.egg-info/not-zip-safe
cloudgrep.egg-info/requires.txt
cloudgrep.egg-info/top_level.txt
tests/__init__.py
tests/test_unit.py