Metadata-Version: 2.1
Name: cloudgrep
Version: 1.0.5
Summary: cloudgrep searches cloud storage
Home-page: https://github.com/cado-security/cloudgrep
Download-URL: https://github.com/cado-security/cloudgrep/archive/refs/heads/main.zip
Author: Cado Security
Author-email: cloudgrep@cadosecurity.com
License: Apache License
Classifier: Intended Audience :: Developers
Classifier: Operating System :: POSIX
Classifier: Programming Language :: Python :: 3
Classifier: Programming Language :: Python :: 3 :: Only
Classifier: Programming Language :: Python :: 3.8
Classifier: Programming Language :: Python :: 3.9
Classifier: Programming Language :: Python :: 3.10
Classifier: Programming Language :: Python :: 3.11
Classifier: Programming Language :: Python :: 3.12
Classifier: Topic :: Software Development :: Libraries
Classifier: Topic :: Utilities
Requires-Python: >=3.8
Provides-Extra: testing
License-File: LICENSE
